xmodel_rest/__init__.py
xmodel_rest/api.py
xmodel_rest/auth.py
xmodel_rest/client.py
xmodel_rest/default_model_urls.py
xmodel_rest/errors.py
xmodel_rest/meta.json
xmodel_rest/model.py
xmodel_rest/session.py
xmodel_rest/settings.py
xmodel_rest/structure.py
xmodel_rest-0.1.1.dist-info/LICENSE
xmodel_rest-0.1.1.dist-info/METADATA
xmodel_rest-0.1.1.dist-info/WHEEL
xmodel_rest-0.1.1.dist-info/RECORD
